[
    {
        "city": "Los Angeles",
        "id": "10773",
        "airport": "Los Angeles International",
        "iata": "LAX",
        "country": "United States",
        "countrycode": "US",
        "state": "California",
        "other1": "USA",
        "other2": "America",
        "other3": "",
        "other4": "",
        "tag": "",
        "time_zone": "America/Los_Angeles"
    },
    {
        "city": "New York",
        "id": "11287",
        "airport": "John F Kennedy Intl",
        "iata": "JFK",
        "country": "United States",
        "countrycode": "US",
        "state": "",
        "other1": "USA",
        "other2": "America",
        "other3": "",
        "other4": "",
        "tag": "",
        "time_zone": "America/New_York"
    },
    {
        "city": "Chicago",
        "id": "13031",
        "airport": "Ohare International",
        "iata": "ORD",
        "country": "United States",
        "countrycode": "US",
        "state": "",
        "other1": "USA",
        "other2": "America",
        "other3": "",
        "other4": "",
        "tag": "",
        "time_zone": "America/Chicago"
    },
    {
        "city": "Boston",
        "id": "8845",
        "airport": "Logan International",
        "iata": "BOS",
        "country": "United States",
        "countrycode": "US",
        "state": "",
        "other1": "USA",
        "other2": "America",
        "other3": "",
        "other4": "",
        "tag": "",
        "time_zone": "America/New_York"
    },
    {
        "city": "Dallas",
        "id": "9381",
        "airport": "Dallas/Ft Worth Intl",
        "iata": "DFW",
        "country": "United States",
        "countrycode": "US",
        "state": "",
        "other1": "USA",
        "other2": "America",
        "other3": "",
        "other4": "",
        "tag": "",
        "time_zone": "America/Chicago"
    },
    {
        "city": "San Francisco",
        "id": "12107",
        "airport": "San Francisco International",
        "iata": "SFO",
        "country": "United States",
        "countrycode": "US",
        "state": "California",
        "other1": "USA",
        "other2": "America",
        "other3": "",
        "other4": "",
        "tag": "",
        "time_zone": "America/Los_Angeles"
    },
    {
        "city": "Newark",
        "id": "13033",
        "airport": "Newark International Airport",
        "iata": "EWR",
        "country": "United States",
        "countrycode": "US",
        "state": "",
        "other1": "USA",
        "other2": "America",
        "other3": "",
        "other4": "",
        "tag": "",
        "time_zone": "America/New_York"
    },
    {
        "city": "Ardmore",
        "id": "8553",
        "airport": "Downtown",
        "iata": "AHD",
        "country": "United States",
        "countrycode": "US",
        "state": "",
        "other1": "amdavad",
        "other2": "",
        "other3": "",
        "other4": "",
        "tag": "",
        "time_zone": ""
    },
    {
        "city": "Washington",
        "id": "13323",
        "airport": "All airports",
        "iata": "WAS",
        "country": "United States",
        "countrycode": "US",
        "state": "",
        "other1": "USA",
        "other2": "America",
        "other3": "",
        "other4": "",
        "tag": "",
        "time_zone": "America/New_York"
    },
    {
        "city": "New York",
        "id": "13211",
        "airport": "All airports",
        "iata": "NYC",
        "country": "United States",
        "countrycode": "US",
        "state": "",
        "other1": "USA",
        "other2": "America",
        "other3": "",
        "other4": "",
        "tag": "",
        "time_zone": "America/New_York"
    },
    {
        "city": "Seattle",
        "id": "12201",
        "airport": "Seattle/tacoma International",
        "iata": "SEA",
        "country": "United States",
        "countrycode": "US",
        "state": "",
        "other1": "USA",
        "other2": "America",
        "other3": "",
        "other4": "",
        "tag": "",
        "time_zone": "America/Los_Angeles"
    },
    {
        "city": "Orlando",
        "id": "11473",
        "airport": "International",
        "iata": "MCO",
        "country": "United States",
        "countrycode": "US",
        "state": "",
        "other1": "USA",
        "other2": "America",
        "other3": "",
        "other4": "",
        "tag": "",
        "time_zone": "America/New_York"
    },
    {
        "city": "Washington",
        "id": "12791",
        "airport": "Ronald Reagan National",
        "iata": "DCA",
        "country": "United States",
        "countrycode": "US",
        "state": "",
        "other1": "USA",
        "other2": "America",
        "other3": "",
        "other4": "",
        "tag": "",
        "time_zone": "America/New_York"
    },
    {
        "city": "Atlanta",
        "id": "8587",
        "airport": "Hartsfield-Jackson Atlanta Int",
        "iata": "ATL",
        "country": "United States",
        "countrycode": "US",
        "state": "",
        "other1": "USA",
        "other2": "America",
        "other3": "",
        "other4": "",
        "tag": "",
        "time_zone": "America/New_York"
    }
]